yttool.py
youtube_tool-1.0.11.dist-info/LICENSE
youtube_tool-1.0.11.dist-info/METADATA
youtube_tool-1.0.11.dist-info/WHEEL
youtube_tool-1.0.11.dist-info/entry_points.txt
youtube_tool-1.0.11.dist-info/top_level.txt
youtube_tool-1.0.11.dist-info/RECORD
